README.rst
setup.py
courseraprogramming/__init__.py
courseraprogramming/main.py
courseraprogramming/utils.py
courseraprogramming.egg-info/PKG-INFO
courseraprogramming.egg-info/SOURCES.txt
courseraprogramming.egg-info/dependency_links.txt
courseraprogramming.egg-info/entry_points.txt
courseraprogramming.egg-info/not-zip-safe
courseraprogramming.egg-info/requires.txt
courseraprogramming.egg-info/top_level.txt
courseraprogramming/commands/__init__.py
courseraprogramming/commands/cat.py
courseraprogramming/commands/common.py
courseraprogramming/commands/config.py
courseraprogramming/commands/grade.py
courseraprogramming/commands/inspect.py
courseraprogramming/commands/ls.py
courseraprogramming/commands/oauth2.py
courseraprogramming/commands/publish.py
courseraprogramming/commands/reregister.py
courseraprogramming/commands/sanity.py
courseraprogramming/commands/upload.py
courseraprogramming/commands/version.py