Metadata-Version: 1.1
Name: courseraprogramming
Version: 0.17.0
Summary: A toolkit to help develop asynchronous graders for Coursera          based on docker images.
Home-page: https://github.com/coursera/courseraprogramming
Author: Brennan Saeta
Author-email: saeta@coursera.org
License: Apache
Keywords: grading programming coursera sdk docker cli tool
Platform: UNKNOWN
Classifier: Development Status :: 5 - Production/Stable
Classifier: License :: OSI Approved :: Apache Software License
Classifier: Programming Language :: Python :: 2.7
